log/__init__.py
log/base.py
log/decorators.py
log/handy-log-sample.yaml
log/handy-log.yaml
log/utils.py
log/__pycache__/__init__.cpython-39.pyc
log/__pycache__/base.cpython-39.pyc
log/__pycache__/decorators.cpython-39.pyc
log/__pycache__/utils.cpython-39.pyc
handy_log-2022.5.5a2.dist-info/LICENSE
handy_log-2022.5.5a2.dist-info/METADATA
handy_log-2022.5.5a2.dist-info/WHEEL
handy_log-2022.5.5a2.dist-info/top_level.txt
handy_log-2022.5.5a2.dist-info/RECORD
