Metadata-Version: 2.1
Name: handy-log
Version: 2022.5.5a2
Summary: Make the log system easier to use
Home-page: https://github.com/nrnn/handy-log
Author: nrnn
Author-email: nrnn_code@yeah.net
License: GNU General Public License v3 (GPLv3)
Project-URL: Bug Tracker, https://github.com/nrnn/handy-log/issues
Keywords: logging,logger,handy-log
Platform: UNKNOWN
Classifier: Programming Language :: Python :: 3
Classifier: License :: OSI Approved :: GNU General Public License v3 (GPLv3)
Classifier: Operating System :: OS Independent
Requires-Python: >=3.6
License-File: LICENSE
